solvency2_data/__init__.py
solvency2_data/alternative_extrapolation.py
solvency2_data/eiopa_data.py
solvency2_data/rfr.py
solvency2_data/scraping.py
solvency2_data/smith_wilson.py
solvency2_data/solvency2_data.cfg
solvency2_data/sqlite_handler.py
solvency2_data/util.py
solvency2_data-0.3.0.dist-info/LICENSE
solvency2_data-0.3.0.dist-info/METADATA
solvency2_data-0.3.0.dist-info/WHEEL
solvency2_data-0.3.0.dist-info/RECORD
