Metadata-Version: 2.3
Name: solvency2-data
Version: 0.3.0
Summary: Package for reading the Solvency 2 Risk-Free Interest Rate Term Structures from the zip-files on the EIOPA website and deriving the term structures for alternative extrapolations
License: MIT
Keywords: solvency2,eiopa,pandas
Author: Willem Jan Willemse
Author-email: w.j.willemse@freedom.nl
Requires-Python: >=3.9, <3.13
Classifier: Development Status :: 3 - Alpha
Classifier: License :: OSI Approved :: MIT License
Classifier: Natural Language :: English
Classifier: Operating System :: OS Independent
Classifier: Programming Language :: Python
Classifier: Programming Language :: Python :: 3.8
Classifier: Programming Language :: Python :: 3.9
Classifier: Programming Language :: Python :: 3.10
Classifier: Programming Language :: Python :: 3.11
Classifier: Programming Language :: Python :: 3.12
Requires-Dist: bs4
Requires-Dist: configparser
Requires-Dist: lxml
Requires-Dist: numpy
Requires-Dist: openpyxl
Requires-Dist: pandas
Requires-Dist: requests
Project-URL: Documentation, https://wjwillemse.github.io/solvency2-data
Project-URL: Homepage, https://wjwillemse.github.io/solvency2-data
Project-URL: Repository, https://github.com/wjwillemse/solvency2-data
